LinuxViMingling30FenzhongRumenjiaochengCYuyanZhongwenwang/README.md
LinuxViMingling30FenzhongRumenjiaochengCYuyanZhongwenwang/__init__.py
LinuxViMingling30FenzhongRumenjiaochengCYuyanZhongwenwang/__main__.py
LinuxViMingling30FenzhongRumenjiaochengCYuyanZhongwenwang/file.epub
LinuxViMingling30FenzhongRumenjiaochengCYuyanZhongwenwang/index.html
LinuxViMingling30FenzhongRumenjiaochengCYuyanZhongwenwang/css/__init__.py
LinuxViMingling30FenzhongRumenjiaochengCYuyanZhongwenwang/css/annotations.css
LinuxViMingling30FenzhongRumenjiaochengCYuyanZhongwenwang/css/main.css
LinuxViMingling30FenzhongRumenjiaochengCYuyanZhongwenwang/css/normalize.css
LinuxViMingling30FenzhongRumenjiaochengCYuyanZhongwenwang/css/popup.css
LinuxViMingling30FenzhongRumenjiaochengCYuyanZhongwenwang/font/__init__.py
LinuxViMingling30FenzhongRumenjiaochengCYuyanZhongwenwang/font/fontello.eot
LinuxViMingling30FenzhongRumenjiaochengCYuyanZhongwenwang/font/fontello.svg
LinuxViMingling30FenzhongRumenjiaochengCYuyanZhongwenwang/font/fontello.ttf
LinuxViMingling30FenzhongRumenjiaochengCYuyanZhongwenwang/font/fontello.woff
LinuxViMingling30FenzhongRumenjiaochengCYuyanZhongwenwang/img/__init__.py
LinuxViMingling30FenzhongRumenjiaochengCYuyanZhongwenwang/img/annotator-glyph-sprite.png
LinuxViMingling30FenzhongRumenjiaochengCYuyanZhongwenwang/img/annotator-icon-sprite.png
LinuxViMingling30FenzhongRumenjiaochengCYuyanZhongwenwang/img/apple-touch-icon.png
LinuxViMingling30FenzhongRumenjiaochengCYuyanZhongwenwang/img/cancelfullscreen.png
LinuxViMingling30FenzhongRumenjiaochengCYuyanZhongwenwang/img/close.png
LinuxViMingling30FenzhongRumenjiaochengCYuyanZhongwenwang/img/fullscreen.png
LinuxViMingling30FenzhongRumenjiaochengCYuyanZhongwenwang/img/loader.gif
LinuxViMingling30FenzhongRumenjiaochengCYuyanZhongwenwang/img/menu-icon.png
LinuxViMingling30FenzhongRumenjiaochengCYuyanZhongwenwang/img/save.png
LinuxViMingling30FenzhongRumenjiaochengCYuyanZhongwenwang/img/saved.png
linux_vi_mingling_30_fenzhong_rumenjiaocheng_c_yuyan_zhongwenwang-2024.3.5.0.dist-info/METADATA
linux_vi_mingling_30_fenzhong_rumenjiaocheng_c_yuyan_zhongwenwang-2024.3.5.0.dist-info/WHEEL
linux_vi_mingling_30_fenzhong_rumenjiaocheng_c_yuyan_zhongwenwang-2024.3.5.0.dist-info/entry_points.txt
linux_vi_mingling_30_fenzhong_rumenjiaocheng_c_yuyan_zhongwenwang-2024.3.5.0.dist-info/top_level.txt
linux_vi_mingling_30_fenzhong_rumenjiaocheng_c_yuyan_zhongwenwang-2024.3.5.0.dist-info/RECORD
